.coveragerc
MANIFEST.in
README.rst
requirements-test.txt
run-tests.sh
setup.py
django_teamwork.egg-info/PKG-INFO
django_teamwork.egg-info/SOURCES.txt
django_teamwork.egg-info/dependency_links.txt
django_teamwork.egg-info/requires.txt
django_teamwork.egg-info/top_level.txt
docs/Makefile
docs/conf.py
docs/contributing.rst
docs/faqs.rst
docs/getting_started.rst
docs/index.rst
docs/make.bat
docs/overview.rst
docs/requirements.txt
docs/todo.rst
docs/usage.rst
docs/_build/doctrees/contributing.doctree
docs/_build/doctrees/environment.pickle
docs/_build/doctrees/faqs.doctree
docs/_build/doctrees/getting_started.doctree
docs/_build/doctrees/index.doctree
docs/_build/doctrees/overview.doctree
docs/_build/doctrees/todo.doctree
docs/_build/doctrees/usage.doctree
docs/_build/html/.buildinfo
docs/_build/html/contributing.html
docs/_build/html/faqs.html
docs/_build/html/genindex.html
docs/_build/html/getting_started.html
docs/_build/html/index.html
docs/_build/html/objects.inv
docs/_build/html/overview.html
docs/_build/html/search.html
docs/_build/html/searchindex.js
docs/_build/html/todo.html
docs/_build/html/usage.html
docs/_build/html/_sources/contributing.txt
docs/_build/html/_sources/faqs.txt
docs/_build/html/_sources/getting_started.txt
docs/_build/html/_sources/index.txt
docs/_build/html/_sources/overview.txt
docs/_build/html/_sources/todo.txt
docs/_build/html/_sources/usage.txt
docs/_build/html/_static/ajax-loader.gif
docs/_build/html/_static/basic.css
docs/_build/html/_static/comment-bright.png
docs/_build/html/_static/comment-close.png
docs/_build/html/_static/comment.png
docs/_build/html/_static/doctools.js
docs/_build/html/_static/down-pressed.png
docs/_build/html/_static/down.png
docs/_build/html/_static/file.png
docs/_build/html/_static/jquery.js
docs/_build/html/_static/minus.png
docs/_build/html/_static/mozilla.css
docs/_build/html/_static/plus.png
docs/_build/html/_static/pygments.css
docs/_build/html/_static/searchtools.js
docs/_build/html/_static/underscore.js
docs/_build/html/_static/up-pressed.png
docs/_build/html/_static/up.png
docs/_build/html/_static/websupport.js
docs/_build/html/_static/css/badge_only.css
docs/_build/html/_static/css/theme.css
