Metadata-Version: 1.1
Name: django-teamwork
Version: 0.2.0
Summary: Django app that offers an authorization backend with support for per-object permissions based on combinations of Teams, Roles, and Policies.
Home-page: http://github.com/lmorchard/django-teamwork
Author: Les Orchard
Author-email: me@lmorchard.com
License: BSD
Platform: UNKNOWN
Classifier: Development Status :: 4 - Beta
Classifier: Framework :: Django
Classifier: Intended Audience :: Developers
Classifier: License :: OSI Approved :: Mozilla Public License 2.0 (MPL 2.0)
Classifier: Operating System :: OS Independent
Classifier: Programming Language :: Python
Classifier: Topic :: Software Development :: Libraries :: Python Modules
